equation_database/__init__.py
equation_database/arxiv_2202_13416/__init__.py
equation_database/doi_10_1103_physrev_176_1700/__init__.py
equation_database/isbn_9780201483628/__init__.py
equation_database/isbn_9780471887416/__init__.py
equation_database/isbn_9780511628788/__init__.py
equation_database/util/__init__.py
equation_database/util/parse.py
equation_database/util/test.py
equation_database-2024.4.4.dist-info/METADATA
equation_database-2024.4.4.dist-info/WHEEL
equation_database-2024.4.4.dist-info/RECORD
